omega_controller/__init__.py
omega_controller/omega_controller.py
omega_controller-0.0.5.dist-info/licenses/LICENSE
omega_controller-0.0.5.dist-info/METADATA
omega_controller-0.0.5.dist-info/WHEEL
omega_controller-0.0.5.dist-info/top_level.txt
omega_controller-0.0.5.dist-info/RECORD
