Metadata-Version: 2.4
Name: omega_controller
Version: 0.0.5
Summary: Lightweight Python driver for Omega CN-series temperature controllers using Modbus over serial
Author-email: Jesse Canavan <canav021@umn.edu>
License-Expression: MIT
Project-URL: Homepage, https://github.com/JesseCan9000/omega-controller-python
Project-URL: Issues, https://github.com/JesseCan9000/omega-controller-python/issues
Classifier: Programming Language :: Python :: 3
Classifier: Operating System :: OS Independent
Requires-Python: >=3.8
License-File: LICENSE
Dynamic: license-file
